fss/.env.example
fss/__init__.py
fss/alembic.ini
fss/apiserver.py
fss/common/__init__.py
fss/common/cache/__init__.py
fss/common/cache/cache.py
fss/common/cache/page_cache.py
fss/common/cache/redis_cache.py
fss/common/cache/redis_manager.py
fss/common/config.py
fss/common/enum/__init__.py
fss/common/enum/enum.py
fss/common/exception/__init__.py
fss/common/exception/exception.py
fss/common/exception/exception_handler.py
fss/common/persistence/__init__.py
fss/common/persistence/base_mapper.py
fss/common/persistence/base_model.py
fss/common/persistence/sqlmodel_impl.py
fss/common/result/__init__.py
fss/common/result/result.py
fss/common/schema/__init__.py
fss/common/schema/schema.py
fss/common/security/__init__.py
fss/common/security/security.py
fss/common/service/__init__.py
fss/common/service/impl/__init__.py
fss/common/service/impl/service_impl.py
fss/common/service/service.py
fss/common/util/__init__.py
fss/common/util/excel.py
fss/common/util/snowflake.py
fss/middleware/__init__.py
fss/middleware/db_session_middleware.py
fss/middleware/ip_block_middleware.py
fss/middleware/jwt_middleware.py
fss/middleware/rate_limit_middleware.py
fss/migrations/db/README.md
fss/migrations/env.py
fss/migrations/script.py.mako
fss/migrations/versions/4cbbaaa2be10_init_db.py
fss/starter/__init__.py
fss/starter/server.py
fss/starter/system/__init__.py
fss/starter/system/api/__init__.py
fss/starter/system/api/v1/__init__.py
fss/starter/system/api/v1/probe_controller.py
fss/starter/system/api/v1/role_controller.py
fss/starter/system/api/v1/user_controller.py
fss/starter/system/enum/__init__.py
fss/starter/system/enum/system.py
fss/starter/system/exception/__init__.py
fss/starter/system/exception/system.py
fss/starter/system/factory/__init__.py
fss/starter/system/factory/service_factory.py
fss/starter/system/factory/sqlsession_factory.py
fss/starter/system/mapper/__init__.py
fss/starter/system/mapper/role_mapper.py
fss/starter/system/mapper/user_mapper.py
fastapi_sqlmodel_starter-1.1.1.dist-info/entry_points.txt
fastapi_sqlmodel_starter-1.1.1.dist-info/LICENSE
fastapi_sqlmodel_starter-1.1.1.dist-info/METADATA
fastapi_sqlmodel_starter-1.1.1.dist-info/WHEEL
fastapi_sqlmodel_starter-1.1.1.dist-info/RECORD
