Metadata-Version: 2.1
Name: fastapi-sqlmodel-starter
Version: 1.1.1
Summary: Fss aims to be one of the best scaffold in PyWeb.
Home-page: https://github.com/tyvekzhang/fastapi-sqlmodel-starter
License: MIT
Keywords: fastapi,sqlmodel,tools,web,scaffold
Author: tyvekZhang
Author-email: tyvekzhang@gmail.com
Maintainer: tyvekZhang
Maintainer-email: tyvekzhang@gmail.com
Requires-Python: >=3.9,<4.0
Classifier: Development Status :: 5 - Production/Stable
Classifier: License :: OSI Approved :: MIT License
Classifier: Programming Language :: Python
Classifier: Programming Language :: Python :: 3
Classifier: Programming Language :: Python :: 3.9
Classifier: Programming Language :: Python :: 3.10
Classifier: Programming Language :: Python :: 3.11
Classifier: Programming Language :: Python :: 3.12
Classifier: Programming Language :: Python :: 3 :: Only
Classifier: Programming Language :: Python :: Implementation :: CPython
Classifier: Programming Language :: Python :: Implementation :: PyPy
Requires-Dist: aiomysql (>=0.2.0,<0.3.0)
Requires-Dist: aiosqlite (>=0.20.0,<0.21.0)
Requires-Dist: alembic (>=1.13.1,<2.0.0)
Requires-Dist: asyncpg (>=0.29.0,<0.30.0)
Requires-Dist: bcrypt (==4.0.1)
Requires-Dist: diskcache (>=5.6.3,<6.0.0)
Requires-Dist: eval-type-backport (>=0.1.3,<0.2.0)
Requires-Dist: fastapi (>=0.110.0,<0.111.0)
Requires-Dist: fastapi-async-sqlalchemy (>=0.6.1,<0.7.0)
Requires-Dist: fastapi-offline (>=1.7.1,<2.0.0)
Requires-Dist: fastapi-pagination (>=0.12.21,<0.13.0)
Requires-Dist: greenlet (>=3.0.3,<4.0.0)
Requires-Dist: loguru (>=0.7.2,<0.8.0)
Requires-Dist: openpyxl (>=3.1.2,<4.0.0)
Requires-Dist: pandas (>=2.2.2,<3.0.0)
Requires-Dist: passlib (>=1.7.4,<2.0.0)
Requires-Dist: python-dotenv (>=1.0.1,<2.0.0)
Requires-Dist: python-jose[cryptography] (>=3.3.0,<4.0.0)
Requires-Dist: python-multipart (>=0.0.9,<0.0.10)
Requires-Dist: redis[hiredis] (>=5.0.3,<6.0.0)
Requires-Dist: slowapi (>=0.1.9,<0.2.0)
Requires-Dist: sqlalchemy-utils (>=0.41.2,<0.42.0)
Requires-Dist: sqlmodel (>=0.0.16,<0.0.17)
Requires-Dist: uvicorn (>=0.29.0,<0.30.0)
Requires-Dist: xlsxwriter (>=3.2.0,<4.0.0)
Project-URL: Documentation, https://github.com/tyvekzhang/fastapi-sqlmodel-starter/wiki
Project-URL: Repository, https://github.com/tyvekzhang/fastapi-sqlmodel-starter
